MANIFEST.in
README.md
diff.txt
requirements.txt
setup.cfg
setup.py
test-requirements.txt
captainhook/__init__.py
captainhook/pre_commit.py
captainhook.egg-info/PKG-INFO
captainhook.egg-info/SOURCES.txt
captainhook.egg-info/dependency_links.txt
captainhook.egg-info/not-zip-safe
captainhook.egg-info/pbr.json
captainhook.egg-info/requires.txt
captainhook.egg-info/top_level.txt
captainhook/checkers/__init__.py
captainhook/checkers/block_branches.py
captainhook/checkers/flake8_checker.py
captainhook/checkers/frosted_checker.py
captainhook/checkers/grep.py
captainhook/checkers/isort_checker.py
captainhook/checkers/merge_marks.py
captainhook/checkers/pdb_checker.py
captainhook/checkers/pylint_checker.py
captainhook/checkers/pylint_docstrings_checker.py
captainhook/checkers/pytest_checker.py
captainhook/checkers/pytest_coverage_checker.py
captainhook/checkers/python3.py
captainhook/checkers/utils.py
scripts/captainhook
test/__init__.py
test/test_config_parser.py
test/test_files.py
test/test_pre_commit.py
test/test_checkers/__init__.py
test/test_checkers/test_pdb.py
test/test_checkers/test_utils.py