Metadata-Version: 1.1
Name: captainhook
Version: 0.8.6
Summary: A collection of git commit hooks
Home-page: https://github.com/alexcouper/captainhook
Author: Alex Couper
Author-email: info@alexcouper.com
License: UNKNOWN
Platform: UNKNOWN
Classifier: Development Status :: 4 - Beta
Classifier: Intended Audience :: Developers
Classifier: License :: OSI Approved :: GNU Library or Lesser General Public License (LGPL)
Classifier: Operating System :: MacOS
Classifier: Operating System :: POSIX
Classifier: Programming Language :: Python :: 2.7
Classifier: Programming Language :: Python :: 3.4
Classifier: Topic :: Software Development :: Libraries :: Python Modules
